LICENSE
MANIFEST.in
README.md
pyproject.toml
requirements-dev.txt
requirements.txt
setup.py
data/audiocaps/train_v2.csv
data/wavcaps/blacklist_audiocaps.full.csv
data/wavcaps/blacklist_clotho.full.csv
data/wavcaps/blacklist_clotho.full.v2.csv
src/aac_datasets/__init__.py
src/aac_datasets/__main__.py
src/aac_datasets/check.py
src/aac_datasets/download.py
src/aac_datasets/info.py
src/aac_datasets.egg-info/PKG-INFO
src/aac_datasets.egg-info/SOURCES.txt
src/aac_datasets.egg-info/dependency_links.txt
src/aac_datasets.egg-info/entry_points.txt
src/aac_datasets.egg-info/requires.txt
src/aac_datasets.egg-info/top_level.txt
src/aac_datasets/datasets/__init__.py
src/aac_datasets/datasets/audiocaps.py
src/aac_datasets/datasets/base.py
src/aac_datasets/datasets/clotho.py
src/aac_datasets/datasets/macs.py
src/aac_datasets/datasets/wavcaps.py
src/aac_datasets/datasets/functional/__init__.py
src/aac_datasets/datasets/functional/audiocaps.py
src/aac_datasets/datasets/functional/clotho.py
src/aac_datasets/datasets/functional/common.py
src/aac_datasets/datasets/functional/macs.py
src/aac_datasets/datasets/functional/wavcaps.py
src/aac_datasets/utils/__init__.py
src/aac_datasets/utils/audioset_mapping.py
src/aac_datasets/utils/cmdline.py
src/aac_datasets/utils/collate.py
src/aac_datasets/utils/collections.py
src/aac_datasets/utils/download.py
src/aac_datasets/utils/globals.py
src/aac_datasets/utils/log_utils.py
src/aac_datasets/utils/type_guards.py
tests/test_datasets_base.py
tests/test_utils_collections.py