Metadata-Version: 2.2
Name: aac-datasets
Version: 0.6.0
Summary: Audio Captioning datasets for PyTorch.
Author-email: "Étienne Labbé (Labbeti)" <labbeti.pub@gmail.com>
Maintainer-email: "Étienne Labbé (Labbeti)" <labbeti.pub@gmail.com>
License: MIT License
Project-URL: Homepage, https://pypi.org/project/aac-datasets/
Project-URL: Documentation, https://aac-datasets.readthedocs.io/
Project-URL: Repository, https://github.com/Labbeti/aac-datasets.git
Project-URL: Changelog, https://github.com/Labbeti/aac-datasets/blob/main/CHANGELOG.md
Project-URL: Tracker, https://github.com/Labbeti/aac-datasets/issues
Keywords: audio,deep-learning,pytorch,dataset,caption,datasets,captioning,audio-captioning
Classifier: Intended Audience :: Developers
Classifier: Intended Audience :: Science/Research
Classifier: License :: OSI Approved :: MIT License
Classifier: Programming Language :: Python :: 3
Classifier: Programming Language :: Python :: 3.8
Classifier: Programming Language :: Python :: 3.9
Classifier: Programming Language :: Python :: 3.10
Classifier: Programming Language :: Python :: 3.11
Classifier: Programming Language :: Python :: 3.12
Classifier: Programming Language :: Python :: 3.13
Classifier: Topic :: Scientific/Engineering
Classifier: Topic :: Scientific/Engineering :: Artificial Intelligence
Classifier: Operating System :: POSIX :: Linux
Requires-Python: >=3.8
License-File: LICENSE
Requires-Dist: huggingface-hub>=0.15.1
Requires-Dist: numpy>=1.21.2
Requires-Dist: py7zr>=0.17.2
Requires-Dist: pyyaml>=6.0
Requires-Dist: soundfile; sys_platform == "win32"
Requires-Dist: torch>=1.10.1
Requires-Dist: torchaudio>=0.10.1
Requires-Dist: tqdm>=4.64.0
Requires-Dist: typing-extensions>=4.6.0
Provides-Extra: dev
Requires-Dist: black==23.3.0; extra == "dev"
Requires-Dist: click==8.0.4; extra == "dev"
Requires-Dist: coverage[toml]; extra == "dev"
Requires-Dist: flake8>=4.0.1; extra == "dev"
Requires-Dist: ipykernel==6.9.1; extra == "dev"
Requires-Dist: isort==5.12.0; extra == "dev"
Requires-Dist: pre-commit; extra == "dev"
Requires-Dist: pytest>=6.2.5; extra == "dev"
Requires-Dist: sphinx; extra == "dev"
Requires-Dist: sphinx-press-theme==0.8.0; extra == "dev"
Requires-Dist: twine==4.0.1; extra == "dev"
